standalone001pyarmor/__init__.py
standalone001pyarmor/core/__init__.py
standalone001pyarmor/core/exfn001add.py
standalone001pyarmor/core/exfn001add.spec
standalone001pyarmor/core/test_fn001add.py
standalone001pyarmor/dist/__init__.py
standalone001pyarmor/dist/exfn001add.py
standalone001pyarmor/dist/test_fn001add_dist.py
standalone001pyarmor/dist/pytransform/__init__.py
standalone001pyarmor/dist/pytransform/_pytransform.dylib
standalone001pyarmor-0.0.15.dist-info/LICENSE
standalone001pyarmor-0.0.15.dist-info/METADATA
standalone001pyarmor-0.0.15.dist-info/WHEEL
standalone001pyarmor-0.0.15.dist-info/top_level.txt
standalone001pyarmor-0.0.15.dist-info/RECORD
